{
  "implements" : [
    "jdk",
    "jdk13"
  ],
  "version" : "13.0.0+33",
  "os" : {
    "Linux" : {
      
    }
  },
  "architecture" : {
    "Arm" : {
      
    }
  },
  "setupSteps" : [
    {
      "SdkDownload" : {
        "url" : "https://github.com/AdoptOpenJDK/openjdk13-binaries/releases/download/jdk-13%2B33/OpenJDK13U-jdk_arm_linux_hotspot_13_33.tar.gz",
        "fileName" : "OpenJDK13U-jdk_arm_linux_hotspot_13_33.tar.gz",
        "hash" : {
          "Sha256" : {
            "value" : "477e1b8d26a220d6d570765e9e0a4a34dbb489fab63a420d0859d173efc59adb"
          }
        }
      }
    },
    {
      "SdkExtract" : {
        "fileName" : "OpenJDK13U-jdk_arm_linux_hotspot_13_33.tar.gz",
        "directory" : "."
      }
    },
    {
      "SdkDelete" : {
        "fileName" : "OpenJDK13U-jdk_arm_linux_hotspot_13_33.tar.gz"
      }
    }
  ],
  "pathDirs" : [
    "jdk-13+33/bin"
  ],
  "env" : {
    "JAVA_HOME" : {
      "Concat" : {
        "values" : [
          {
            "SdkDirectory" : {
              
            }
          },
          {
            "OfString" : {
              "value" : "/jdk-13+33"
            }
          }
        ]
      }
    }
  },
  "configFileTemplates" : null
}